datasiphon/__init__.py
datasiphon/sql_filter.py
datasiphon/core/__init__.py
datasiphon/core/_exc.py
datasiphon/core/_filter_core.py
datasiphon-0.3.11.dist-info/METADATA
datasiphon-0.3.11.dist-info/WHEEL
datasiphon-0.3.11.dist-info/top_level.txt
datasiphon-0.3.11.dist-info/RECORD
