Metadata-Version: 2.2
Name: datasiphon
Version: 0.3.11
Summary: Dynamic building of filtered database queries
Home-page: https://github.com/Nemulo/libs-datasiphon
Author: Marek Nemeth
Author-email: 99m.nemeth@gmail.com
Project-URL: Documentation, https://github.com/Nemulo/libs-datasiphon/blob/main/README.md
Project-URL: Bug Reports, https://github.com/Nemulo/libs-datasiphon/issues
Project-URL: Source, https://github.com/Nemulo/libs-datasiphon
Keywords: database,sql,filtering,query
Classifier: License :: OSI Approved :: MIT License
Classifier: Operating System :: OS Independent
Classifier: Development Status :: 4 - Beta
Classifier: Intended Audience :: Developers
Classifier: Programming Language :: Python :: 3
Classifier: Typing :: Typed
Requires-Python: >=3.10, <4
Requires-Dist: sqlalchemy>=2.0.0
Requires-Dist: qstion>=1.1.2
Dynamic: author
Dynamic: author-email
Dynamic: classifier
Dynamic: description
Dynamic: description-content-type
Dynamic: home-page
Dynamic: keywords
Dynamic: project-url
Dynamic: requires-dist
Dynamic: requires-python
Dynamic: summary
